{"akuoumaru":{"rarity":4},"alley_hunter":{"rarity":4},"amenoma_kageuchi":{"rarity":4},"amos_bow":{"rarity":5},"apprentices_notes":{"rarity":1},"aqua_simulacra":{"rarity":5},"aquila_favonia":{"rarity":5},"a_thousand_floating_dreams":{"rarity":5},"beginners_protector":{"rarity":1},"blackcliff_agate":{"rarity":4},"blackcliff_longsword":{"rarity":4},"blackcliff_pole":{"rarity":4},"blackcliff_slasher":{"rarity":4},"blackcliff_warbow":{"rarity":4},"black_tassel":{"rarity":3},"bloodtainted_greatsword":{"rarity":3},"calamity_queller":{"rarity":5},"cinnabar_spindle":{"rarity":4},"compound_bow":{"rarity":4},"cool_steel":{"rarity":3},"crescent_pike":{"rarity":4},"dark_iron_sword":{"rarity":3},"deathmatch":{"rarity":4},"debate_club":{"rarity":3},"dodoco_tales":{"rarity":4},"dragons_bane":{"rarity":4},"dragonspine_spear":{"rarity":4},"dull_blade":{"rarity":1},"elegy_for_the_end":{"rarity":5},"emerald_orb":{"rarity":3},"end_of_the_line":{"rarity":4},"engulfing_lightning":{"rarity":5},"everlasting_moonglow":{"rarity":5},"eye_of_perception":{"rarity":4},"fading_twilight":{"rarity":4},"favonius_codex":{"rarity":4},"favonius_greatsword":{"rarity":4},"favonius_lance":{"rarity":4},"favonius_sword":{"rarity":4},"favonius_warbow":{"rarity":4},"ferrous_shadow":{"rarity":3},"festering_desire":{"rarity":4},"fillet_blade":{"rarity":3},"forest_regalia":{"rarity":4},"freedom_sworn":{"rarity":5},"frostbearer":{"rarity":4},"fruit_of_fulfillment":{"rarity":4},"hakushin_ring":{"rarity":4},"halberd":{"rarity":3},"hamayumi":{"rarity":4},"haran_geppaku_futsu":{"rarity":5},"harbinger_of_dawn":{"rarity":3},"hunters_bow":{"rarity":1},"hunters_path":{"rarity":5},"iron_point":{"rarity":2},"iron_sting":{"rarity":4},"kagotsurube_isshin":{"rarity":4},"kaguras_verity":{"rarity":5},"katsuragikiri_nagamasa":{"rarity":4},"key_of_khaj_nisut":{"rarity":5},"kings_squire":{"rarity":4},"kitain_cross_spear":{"rarity":4},"lions_roar":{"rarity":4},"lithic_blade":{"rarity":4},"lithic_spear":{"rarity":4},"lost_prayer_to_the_sacred_winds":{"rarity":5},"luxurious_sea_lord":{"rarity":4},"magic_guide":{"rarity":3},"makhaira_aquamarine":{"rarity":4},"mappa_mare":{"rarity":4},"memory_of_dust":{"rarity":5},"messenger":{"rarity":3},"missive_windspear":{"rarity":4},"mistsplitter_reforged":{"rarity":5},"mitternachts_waltz":{"rarity":4},"moonpiercer":{"rarity":4},"mouuns_moon":{"rarity":4},"oathsworn_eye":{"rarity":4},"old_mercs_pal":{"rarity":2},"otherworldly_story":{"rarity":3},"pocket_grimoire":{"rarity":2},"polar_star":{"rarity":5},"predator":{"rarity":4},"primordial_jade_cutter":{"rarity":5},"primordial_jade_winged_spear":{"rarity":5},"prized_isshin_blade":{"rarity":4},"prototype_amber":{"rarity":4},"prototype_archaic":{"rarity":4},"prototype_crescent":{"rarity":4},"prototype_rancour":{"rarity":4},"prototype_starglitter":{"rarity":4},"rainslasher":{"rarity":4},"raven_bow":{"rarity":3},"recurve_bow":{"rarity":3},"redhorn_stonethresher":{"rarity":5},"royal_bow":{"rarity":4},"royal_greatsword":{"rarity":4},"royal_grimoire":{"rarity":4},"royal_longsword":{"rarity":4},"royal_spear":{"rarity":4},"rust":{"rarity":4},"sacrificial_bow":{"rarity":4},"sacrificial_fragments":{"rarity":4},"sacrificial_greatsword":{"rarity":4},"sacrificial_sword":{"rarity":4},"sapwood_blade":{"rarity":4},"seasoned_hunters_bow":{"rarity":2},"serpent_spine":{"rarity":4},"sharpshooters_oath":{"rarity":3},"silver_sword":{"rarity":2},"skyrider_greatsword":{"rarity":3},"skyrider_sword":{"rarity":3},"skyward_atlas":{"rarity":5},"skyward_blade":{"rarity":5},"skyward_harp":{"rarity":5},"skyward_pride":{"rarity":5},"skyward_spine":{"rarity":5},"slingshot":{"rarity":3},"snow_tombed_starsilver":{"rarity":4},"solar_pearl":{"rarity":4},"song_of_broken_pines":{"rarity":5},"staff_of_homa":{"rarity":5},"staff_of_the_scarlet_sands":{"rarity":5},"summit_shaper":{"rarity":5},"sword_of_descension":{"rarity":4},"the_alley_flash":{"rarity":4},"the_bell":{"rarity":4},"the_black_sword":{"rarity":4},"the_catch":{"rarity":4},"the_flute":{"rarity":4},"the_stringless":{"rarity":4},"the_unforged":{"rarity":5},"the_viridescent_hunt":{"rarity":4},"the_widsith":{"rarity":4},"thrilling_tales_of_dragon_slayers":{"rarity":3},"thundering_pulse":{"rarity":5},"toukabou_shigure":{"rarity":4},"travelers_handy_sword":{"rarity":3},"tulaytullahs_remembrance":{"rarity":5},"twin_nephrite":{"rarity":3},"vortex_vanquisher":{"rarity":5},"wandering_evenstar":{"rarity":4},"waster_greatsword":{"rarity":1},"wavebreakers_fin":{"rarity":4},"whiteblind":{"rarity":4},"white_iron_greatsword":{"rarity":3},"white_tassel":{"rarity":3},"windblume_ode":{"rarity":4},"wine_and_song":{"rarity":4},"wolfs_gravestone":{"rarity":5},"xiphos_moonlight":{"rarity":4},"light_of_foliar_incision":{"rarity":5},"beacon_of_the_reed_sea":{"rarity":5},"mailed_flower":{"rarity":4},"jadefalls_splendor":{"rarity":5},"ballad_of_the_fjords":{"rarity":4},"finale_of_the_deep":{"rarity":4},"fleuve_cendre_ferryman":{"rarity":4},"flowing_purity":{"rarity":4},"rightful_reward":{"rarity":4},"sacrificial_jade":{"rarity":4},"scion_of_the_blazing_sun":{"rarity":4},"song_of_stillness":{"rarity":4},"talking_stick":{"rarity":4},"the_first_great_magic":{"rarity":5},"tidal_shadow":{"rarity":4},"wolf_fang":{"rarity":4},"ballad_of_the_boundless_blue":{"rarity":4},"cashflow_supervision":{"rarity":5},"portable_power_saw":{"rarity":4},"prospectors_drill":{"rarity":4},"range_gauge":{"rarity":4},"the_dockhands_assistant":{"rarity":4},"tome_of_the_eternal_flow":{"rarity":5},"splendor_of_tranquil_waters":{"rarity":5},"sword_of_narzissenkreuz":{"rarity":4},"ultimate_overlords_mega_magic_sword":{"rarity":4},"verdict":{"rarity":5}}